LICENSE
MANIFEST.in
README.rst
setup.py
django_credits/__init__.py
django_credits/admin.py
django_credits/apps.py
django_credits/models.py
django_credits.egg-info/PKG-INFO
django_credits.egg-info/SOURCES.txt
django_credits.egg-info/dependency_links.txt
django_credits.egg-info/not-zip-safe
django_credits.egg-info/requires.txt
django_credits.egg-info/top_level.txt
django_credits/migrations/0001_initial.py
django_credits/migrations/__init__.py
django_credits/migrations/__pycache__/0001_initial.cpython-35.pyc
django_credits/migrations/__pycache__/__init__.cpython-35.pyc
django_credits/static/css/djangoCredits.css
django_credits/static/js/djangoCredits.js
django_credits/templates/django_credits.html
django_credits/templatetags/__init__.py
django_credits/templatetags/django_credits.py
django_credits/templatetags/__pycache__/__init__.cpython-35.pyc
django_credits/templatetags/__pycache__/django_credits.cpython-35.pyc
django_credits/templatetags/__pycache__/django_credits_flymake.cpython-35.pyc